intmath/__init__.py
intmath-0.1.0.dist-info/licenses/LICENSE
intmath-0.1.0.dist-info/METADATA
intmath-0.1.0.dist-info/WHEEL
intmath-0.1.0.dist-info/top_level.txt
intmath-0.1.0.dist-info/zip-safe
intmath-0.1.0.dist-info/RECORD
